config.py
index.py
setup.py
algoleap_dynamic_prompts.egg-info/PKG-INFO
algoleap_dynamic_prompts.egg-info/SOURCES.txt
algoleap_dynamic_prompts.egg-info/dependency_links.txt
algoleap_dynamic_prompts.egg-info/entry_points.txt
algoleap_dynamic_prompts.egg-info/requires.txt
algoleap_dynamic_prompts.egg-info/top_level.txt